soundhub/__init__.py
soundhub/asr.py
soundhub/audio.py
soundhub/caption.py
soundhub/retrieve.py
soundhub/version.py
soundhub-1.0.0.dist-info/LICENSE
soundhub-1.0.0.dist-info/METADATA
soundhub-1.0.0.dist-info/WHEEL
soundhub-1.0.0.dist-info/top_level.txt
soundhub-1.0.0.dist-info/RECORD
