Metadata-Version: 2.1
Name: soundhub
Version: 1.0.0
Summary: SoundHub is an AI audio framework.
Home-page: https://github.com/Yuan-ManX/SoundHub
Author: Yuan Man
Author-email: ym1076302261@gmail.com
License: MIT
Keywords: audio music machinelearning deeplearning artificialintelligence neuralnetworks dataprocessing art-techconvergence
Platform: UNKNOWN
Classifier: Development Status :: 3 - Alpha
Classifier: Intended Audience :: Developers
Classifier: Intended Audience :: Science/Research
Classifier: License :: OSI Approved :: MIT License
Classifier: Topic :: Scientific/Engineering :: Artificial Intelligence
Classifier: Topic :: Multimedia :: Sound/Audio :: Analysis
Classifier: Programming Language :: Python :: 3
Classifier: Programming Language :: Python :: 3.6
Classifier: Programming Language :: Python :: 3.7
Classifier: Programming Language :: Python :: 3.8
Classifier: Programming Language :: Python :: 3.9
Classifier: Programming Language :: Python :: 3.10
Classifier: Programming Language :: Python :: 3.11
License-File: LICENSE
Requires-Dist: transformers
Requires-Dist: pydub
Requires-Dist: msclap
